polite_config/__init__.py
polite_config/appdirs.py
polite_config/configuration.py
polite_config/paths.py
polite_config-1.0.0.dist-info/LICENSE.txt
polite_config-1.0.0.dist-info/LICENSES/APPDIRS_LICENSE.txt
polite_config-1.0.0.dist-info/METADATA
polite_config-1.0.0.dist-info/WHEEL
polite_config-1.0.0.dist-info/RECORD
