Metadata-Version: 2.1
Name: polite-config
Version: 1.0.0
Summary: Easy functions for paths, logging and configuration files
Home-page: https://github.com/DTOcean/dtocean
License: MIT
Author: Mathew Toppper
Author-email: damm_horse@yahoo.co.uk
Requires-Python: >=3.13,<4.0
Classifier: License :: OSI Approved :: MIT License
Classifier: Operating System :: OS Independent
Classifier: Programming Language :: Python :: 3
Classifier: Programming Language :: Python :: 3.13
Requires-Dist: configobj (>=5.0.9,<6.0.0)
Requires-Dist: pyyaml (>=6.0.2,<7.0.0)
Project-URL: Bug Tracker, https://github.com/DTOcean/dtocean/issues
Project-URL: Repository, https://github.com/DTOcean/dtocean
